<?xml version="1.0" encoding="utf-8"?>
<odoo>
    <data>
        <template id="account.report_invoice_document">
            <t t-call="web.external_layout">
                <t t-set="o" t-value="o.with_context(lang=lang)" />
                <t t-set="address">
                    <address t-field="o.partner_id" t-options='{"widget": "contact", "fields": ["address", "name"], "no_marker": True}' />
                    <div t-if="o.partner_id.vat" class="mt16">
                        <t t-if="o.company_id.country_id.vat_label" t-esc="o.company_id.country_id.vat_label" id="inv_tax_id_label"/>
                        <t t-else="">Tax ID</t>: <span t-field="o.partner_id.vat"/></div>
                </t>
                <div class="page">
                    <table class="table table-condensed">
                        <tr>
                            <td width="50%" rowspan="3" 
                                style="text-align:left;vertical-align:middle;border:0px;padding:5px;font-size:36px;">
                                FAKTUR PENJUALAN
                            </td>
                            <td width="20%" rowspan="3" 
                                style="text-align:center;vertical-align:bottom;border:0px;padding:0px;font-size:14px;">
                                <img src='v14_print/static/description/logo_central.png' 
                                    style="text-align:left;max-width:80%;vertical-align:bottom;"/>
                            </td>             
                            <td width="30%" class="text-justify"
                                style="font-size:16px; text-align:left;vertical-align:bottom;border:0px;padding:1px;">  
                                Komplek Ruko Mahkota Mas
                            </td>
                        </tr>         
                        <tr>
                            <td style="font-size:16px; text-align:left;vertical-align:bottom;border:0px;padding:1px;">
                                Blok J-46, Cikokol, Tangerang
                            </td>
                        </tr>
                        <tr>
                            <td style="font-size:16px; text-align:left;vertical-align:top;border:0px;padding:1px;">
                                Telp/Fax : (021) 55703111
                            </td>
                        </tr>
                    </table>
                    
                    <table class="table table-condensed" style="margin-top:0px;">
                        <tr>                                                    
                            <td width="15%"
                                style="font-size:14px;
                                padding:5px;
                                text-align:left;
                                border:0px;">     
                                Kepada
                            </td>                       
                            <td width="35%" 
                                style="font-size:14px;
                                padding:5px;
                                text-align:left;
                                border:0px;">
                                <strong>: <span t-field="o.partner_id.name"/></strong>
                            </td>                       
                            <td width="5%" 
                                style="font-size:14px;
                                padding:5px;
                                text-align:left;
                                border:0px;">
                            </td>
                            <td width="15%"
                                style="font-size:14px;
                                padding:5px;
                                text-align:left;
                                border:0px;">     
                                No. Invoice
                            </td>                       
                            <td width="35%" 
                                style="font-size:14px;
                                padding:5px;
                                text-align:left;
                                border:0px;">
                                <strong>: <span t-field="o.name"/></strong>
                            </td>
                        </tr>   
                        <tr>                                                    
                            <td width="15%"
                                style="font-size:14px;
                                padding:5px;
                                text-align:left;
                                border:0px;">     
                                
                            </td>                       
                            <td width="35%" 
                                style="font-size:14px;
                                padding:5px;
                                text-align:left;
                                border:0px;">
                                
                            </td>                       
                            <td width="5%" 
                                style="font-size:14px;
                                padding:5px;
                                text-align:left;
                                border:0px;">
                            </td>
                            <td width="15%"
                                style="font-size:14px;
                                padding:5px;
                                text-align:left;
                                border:0px;">     
                                Tanggal
                            </td>                       
                            <td width="35%" 
                                style="font-size:14px;
                                padding:5px;
                                text-align:left;
                                border:0px;">
                                : <span t-field="o.invoice_date"/>
                            </td>
                        </tr>   
                        <tr>                                                    
                            <td width="15%"
                                style="font-size:14px;
                                padding:5px;
                                text-align:left;
                                border:0px;">     
                                Alamat
                            </td>                       
                            <td width="35%" 
                                style="font-size:14px;
                                padding:5px;
                                text-align:left;
                                border:0px;">
                                : <span t-field="o.partner_id.street"/>
                            </td>                       
                            <td width="5%" 
                                style="font-size:14px;
                                padding:5px;
                                text-align:left;
                                border:0px;">
                            </td>
                            <td width="15%"
                                style="font-size:14px;
                                padding:5px;
                                text-align:left;
                                border:0px;">     
                                ID Cust
                            </td>                       
                            <td width="35%" 
                                style="font-size:14px;
                                padding:5px;
                                text-align:left;
                                border:0px;">
                                : <span t-field="o.partner_id.ref"/>
                            </td>
                        </tr>   
                    </table>

                    <table class="table table-condensed" style="margin-top:0px;">
                        <tr>                                                    
                            <td width="5%"
                                style="font-size:14px;
                                padding:5px;
                                text-align:center;
                                border:1px solid black;">     
                                <strong>No.</strong>
                            </td>
                            <td width="35%" 
                                style="font-size:14px;
                                padding:5px;
                                text-align:center;
                                border:1px solid black;">
                                <strong>Deskripsi</strong>
                            </td>                       
                            <td width="10%"
                                style="font-size:14px;
                                padding:5px;
                                text-align:center;
                                border:1px solid black;">
                                <strong>Jumlah</strong>
                            </td>
                            <td width="10%"
                                style="font-size:14px;
                                padding:5px;
                                text-align:center;
                                border:1px solid black;">     
                                <strong>Unit</strong>
                            </td>                       
                            <td width="10%" 
                                style="font-size:14px;
                                padding:5px;
                                text-align:center;
                                border:1px solid black;">
                                <strong>Harga</strong>
                            </td>
                            <td width="15%" 
                                style="font-size:14px;
                                padding:5px;
                                text-align:center;
                                border:1px solid black;">
                                <strong>Subtotal</strong>
                            </td>
                            <td width="10%" 
                                style="font-size:14px;
                                padding:5px;
                                text-align:center;
                                border:1px solid black;">
                                <strong>Pajak</strong>
                            </td>
                        </tr>   
                        <t t-set="i" t-value="1" />
                        <t t-foreach="o.invoice_line_ids" t-as="line">
                            <tr>
                                <td style="font-size:14px;
                                    padding:5px;
                                    text-align:center;
                                    border:1px solid black;">
                                    <span t-esc="i"/> 
                                    <t t-set="i" t-value="i+1"/>
                                </td>
                                <td style="font-size:14px;
                                    padding:5px;
                                    text-align:center;
                                    border:1px solid black;">
                                    <span t-field="line.product_id.name"/>
                                </td>
                                <td style="font-size:14px;
                                    padding:5px;
                                    text-align:right;
                                    border:1px solid black;">
                                    <span t-esc="'{0:,.0f}'.format(line.quantity)"/>
                                </td>
                                <td style="font-size:14px;
                                    padding:5px;
                                    text-align:center;
                                    border:1px solid black;">
                                    <span t-field="line.product_uom_id.name"/>
                                </td>
                                <td style="font-size:14px;
                                    padding:5px;
                                    text-align:right;
                                    border:1px solid black;">
                                    <span t-esc="'{0:,.0f}'.format(line.price_unit)"/>
                                </td>
                                <td style="font-size:14px;
                                    padding:5px;
                                    text-align:right;
                                    border:1px solid black;">
                                    <span t-esc="'{0:,.0f}'.format(line.price_subtotal)"/>
                                </td>
                                <td style="font-size:14px;
                                    padding:5px;
                                    text-align:center;
                                    border:1px solid black;">
                                    <span t-field="line.tax_ids"/>
                                </td>
                            </tr>
                        </t>
                    </table>
                    <table class="table table-condensed" style="margin-top:5px;">
                        <tr>
                            <td width="100%" style="border:0px;font-size:12px;padding:2px;">
                                <i>Terbilang : <span t-field="o.amount_total_terbilang"/></i>
                            </td>
                        </tr>
                    </table>
                    <table class="table table-condensed" style="margin-top:20px;">
                        <tr>                                                    
                            <td width="60%"
                                style="font-size:12px;
                                padding:2px;
                                text-align:left;
                                border-top:1px solid black;
                                border-bottom:0px;
                                border-left:1px solid black;
                                border-right:1px solid black;">     
                                Pembayaran harap melalui Bank dgn mencantumkan no invoice kepada Rekening
                            </td>
                            <td width="5%"
                                style="font-size:14px;
                                padding:5px;
                                text-align:left;
                                border:0px;">
                            </td>
                            <td width="14%"
                                style="font-size:14px;
                                padding:5px;
                                text-align:left;
                                border:0px;">     
                                <strong>Sub Total</strong>
                            </td>
                            <td width="3%"
                                style="font-size:14px;
                                padding:5px;
                                text-align:left;
                                border:0px;">     
                                <strong>:</strong>
                            </td>
                            <td width="35%"
                                style="font-size:14px;
                                padding:5px;
                                text-align:right;
                                border:0px;">     
                                <strong><span t-field="o.amount_untaxed"/></strong>
                            </td>
                        </tr>
                        <tr>                                                    
                            <td style="font-size:12px;
                                padding:2px;
                                text-align:left;
                                border-top:0px;
                                border-bottom:0px;
                                border-left:1px solid black;
                                border-right:1px solid black;">
                                CENTRAL JAYA CV
                            </td>
                            <td style="font-size:14px;
                                padding:5px;
                                text-align:left;
                                border:0px;">
                            </td>
                            <td style="font-size:14px;
                                padding:5px;
                                text-align:left;
                                border:0px;">     
                                <strong>Pajak</strong>
                            </td>
                            <td style="font-size:14px;
                                padding:5px;
                                text-align:left;
                                border:0px;">     
                                <strong>:</strong>
                            </td>
                            <td style="font-size:14px;
                                padding:5px;
                                text-align:right;
                                border:0px;">     
                                <strong><span t-field="o.amount_tax"/></strong>
                            </td>
                        </tr>
                        <tr>                                                    
                            <td style="font-size:12px;
                                padding:2px;
                                text-align:left;
                                border-top:0px;
                                border-bottom:0px;
                                border-left:1px solid black;
                                border-right:1px solid black;">
                                Bank BCA Cab. Sunter Mall
                            </td>
                            <td style="font-size:14px;
                                padding:5px;
                                text-align:left;
                                border:0px;">     
                            </td>
                            <td style="font-size:14px;
                                padding:5px;
                                text-align:left;
                                border-top:0px;
                                border-bottom:2px solid black;
                                border-left:0px;
                                border-right:0px;">       
                                <strong>Total</strong>
                            </td>
                            <td style="font-size:14px;
                                padding:5px;
                                text-align:left;
                                border-top:0px;
                                border-bottom:2px solid black;
                                border-left:0px;
                                border-right:0px;">  
                                <strong>:</strong>
                            </td>
                            <td style="font-size:14px;
                                padding:5px;
                                text-align:right;
                                border-top:0px;
                                border-bottom:2px solid black;
                                border-left:0px;
                                border-right:0px;">  
                                <strong><span t-field="o.amount_total"/></strong>
                            </td>
                        </tr>
                        <tr>                                                    
                            <td style="font-size:12px;
                                padding:2px;
                                text-align:left;
                                border-top:0px;
                                border-bottom:1px solid black;
                                border-left:1px solid black;
                                border-right:1px solid black;">  
                                No. Rekening : 4284-888-444
                            </td>
                            <td style="font-size:14px;
                                padding:5px;
                                text-align:left;
                                border:0px;">
                            </td>
                            <td style="font-size:14px;
                                padding:5px;
                                text-align:left;
                                border:0px;">     
                            </td>
                            <td style="font-size:14px;
                                padding:5px;
                                text-align:left;
                                border:0px;">     
                            </td>
                            <td style="font-size:14px;
                                padding:5px;
                                text-align:left;
                                border:0px;">     
                            </td>
                        </tr>
                        <tr height="130px" style="margin-top:50px;">                                                    
                            <td style="font-size:12px;
                                padding:2px;
                                text-align:left;
                                border:0px;">  
                            </td>
                            <td style="font-size:14px;
                                padding:5px;
                                text-align:left;
                                border:0px;">
                            </td>
                            <td colspan="3" style="font-size:14px;
                                padding:5px;
                                text-align:center;
                                border:0px;">
                                <strong>CV. CENTRAL JAYA</strong>     
                            </td>
                        </tr>
                        <tr style="margin-top:20px;">                                                    
                            <td style="font-size:12px;
                                padding:2px;
                                text-align:left;
                                border:0px;">  
                            </td>
                            <td style="font-size:14px;
                                padding:5px;
                                text-align:left;
                                border:0px;">
                            </td>
                            <td colspan="3" style="font-size:14px;
                                padding:5px;
                                text-align:center;
                                border-top:0px;
                                border-bottom:1px solid black;
                                border-left:0px;
                                border-right:0px;">  
                                <strong>Kwe Chriscope</strong>     
                            </td>
                        </tr>
                        <tr style="margin-top:20px;">                                                    
                            <td style="font-size:12px;
                                padding:2px;
                                text-align:left;
                                border:0px;">  
                            </td>
                            <td style="font-size:14px;
                                padding:5px;
                                text-align:left;
                                border:0px;">
                            </td>
                            <td colspan="3" style="font-size:14px;
                                padding:5px;
                                text-align:center;
                                border-top:0px;
                                border-bottom:0px;
                                border-left:0px;
                                border-right:0px;">  
                                Direktur     
                            </td>
                        </tr>
                    </table>
                </div>
            </t>
        </template>

    </data>
</odoo>
